LICENSE
MANIFEST.in
README.rst
setup.cfg
setup.py
src/downloadcounter/__init__.py
src/downloadcounter/apps.py
src/downloadcounter/models.py
src/downloadcounter/signals.py
src/downloadcounter/migrations/0001_initial.py
src/downloadcounter/migrations/__init__.py
src/downloadcounter/templates/.DS_Store
src/downloadcounter/templates/wagtaildocs/.DS_Store
src/downloadcounter/templates/wagtaildocs/documents/list.html
src/wagtail_download_counter.egg-info/PKG-INFO
src/wagtail_download_counter.egg-info/SOURCES.txt
src/wagtail_download_counter.egg-info/dependency_links.txt
src/wagtail_download_counter.egg-info/requires.txt
src/wagtail_download_counter.egg-info/top_level.txt