Metadata-Version: 1.1
Name: wagtail-download-counter
Version: 0.0.1
Summary: A Wagtail add-on to to keep track of the number of downloads per file
Home-page: https://www.fourdigits.nl/
Author: Four Digits BV
Author-email: info@fourdigits.nl
License: BSD
Platform: UNKNOWN
Classifier: Development Status :: 1 - Planning
Classifier: Environment :: Web Environment
Classifier: Intended Audience :: Developers
Classifier: License :: OSI Approved :: BSD License
Classifier: Operating System :: OS Independent
Classifier: Programming Language :: Python
Classifier: Programming Language :: Python :: 2
Classifier: Programming Language :: Python :: 2.7
Classifier: Programming Language :: Python :: 3
Classifier: Programming Language :: Python :: 3.3
Classifier: Programming Language :: Python :: 3.4
Classifier: Programming Language :: Python :: 3.5
Classifier: Framework :: Django
Classifier: Framework :: Django :: 1.8
Classifier: Framework :: Django :: 1.9
Classifier: Topic :: Internet :: WWW/HTTP :: Site Management
